sas_log_viewer/__init__.py
sas_log_viewer/_version.py
sas_log_viewer/labextension/build_log.json
sas_log_viewer/labextension/package.json
sas_log_viewer/labextension/static/108.70580fea9037bd14b23d.js
sas_log_viewer/labextension/static/174.148a9c38011d5256e62b.js
sas_log_viewer/labextension/static/534.ed468e0622ba96d66fe5.js
sas_log_viewer/labextension/static/lib_index_js.05a4bbb7ef0f3666a0dc.js
sas_log_viewer/labextension/static/lib_index_js.05a4bbb7ef0f3666a0dc.js.map
sas_log_viewer/labextension/static/lib_index_js.78a89d0e89b9e76ed5a9.js
sas_log_viewer/labextension/static/lib_index_js.78a89d0e89b9e76ed5a9.js.map
sas_log_viewer/labextension/static/lib_index_js.9f8702919751297b8093.js
sas_log_viewer/labextension/static/lib_index_js.9f8702919751297b8093.js.map
sas_log_viewer/labextension/static/lib_index_js.b690245f87a3132d2ca8.js
sas_log_viewer/labextension/static/lib_index_js.b690245f87a3132d2ca8.js.map
sas_log_viewer/labextension/static/lib_index_js.f1abfa74696980b7b1f3.js
sas_log_viewer/labextension/static/lib_index_js.f1abfa74696980b7b1f3.js.map
sas_log_viewer/labextension/static/node_modules_css-loader_dist_cjs_js_style_base_css-node_modules_style-loader_dist_runtime_inj-d795f2.df4131f5587adc275091.js
sas_log_viewer/labextension/static/node_modules_css-loader_dist_cjs_js_style_base_css-node_modules_style-loader_dist_runtime_inj-d795f2.df4131f5587adc275091.js.map
sas_log_viewer/labextension/static/remoteEntry.67719da3f1bfc1d7a933.js.map
sas_log_viewer/labextension/static/remoteEntry.74af05ab179c5319d2f2.js
sas_log_viewer/labextension/static/remoteEntry.77e0a7c07c53d8a22727.js
sas_log_viewer/labextension/static/remoteEntry.77e0a7c07c53d8a22727.js.map
sas_log_viewer/labextension/static/remoteEntry.7d2926b994a577d139b0.js.map
sas_log_viewer/labextension/static/remoteEntry.d1272e8e556d0ffc4071.js
sas_log_viewer/labextension/static/remoteEntry.d1272e8e556d0ffc4071.js.map
sas_log_viewer/labextension/static/remoteEntry.dae5a91ef6f4d3519c18.js.map
sas_log_viewer-0.2.0.dist-info/LICENSE
sas_log_viewer-0.2.0.dist-info/METADATA
sas_log_viewer-0.2.0.dist-info/WHEEL
sas_log_viewer-0.2.0.dist-info/top_level.txt
sas_log_viewer-0.2.0.dist-info/RECORD
